slg_utilities/__init__.py
slg_utilities/access.py
slg_utilities/config.py
slg_utilities/email_handler.py
slg_utilities/file_operations.py
slg_utilities/helpers.py
slg_utilities/image_processor.py
slg_utilities/mongo_engine.py
slg_utilities/scraping_engine.py
slg_utilities/table_helpers.py
slg_utilities/decorators/__init__.py
slg_utilities/decorators/decorators.py
slg_utilities/decorators/files.py
slg_utilities/decorators/logging.py
slg_utilities/decorators/profilers.py
slg_utilities/tests/__init__.py
slg_utilities/tests/test_file_operations.py
slg_utilities-0.4.23.dist-info/METADATA
slg_utilities-0.4.23.dist-info/WHEEL
slg_utilities-0.4.23.dist-info/top_level.txt
slg_utilities-0.4.23.dist-info/RECORD
